pyscramble/__init__.py
pyscramble/_core.cpython-311-i386-linux-gnu.so
pyscramble/_core.pyi
pyscramble-0.1.0.dist-info/METADATA
pyscramble-0.1.0.dist-info/WHEEL
pyscramble-0.1.0.dist-info/licenses/LICENSE
pyscramble-0.1.0.dist-info/RECORD
