Metadata-Version: 2.4
Name: pyscramble
Version: 0.1.0
Classifier: Development Status :: 4 - Beta
Classifier: Intended Audience :: Developers
Classifier: Intended Audience :: Science/Research
Classifier: License :: OSI Approved :: MIT License
Classifier: Operating System :: OS Independent
Classifier: Programming Language :: Python :: 3
Classifier: Programming Language :: Python :: 3.8
Classifier: Programming Language :: Python :: 3.9
Classifier: Programming Language :: Python :: 3.10
Classifier: Programming Language :: Python :: 3.11
Classifier: Programming Language :: Python :: 3.12
Classifier: Programming Language :: Python :: 3.13
Classifier: Programming Language :: Python :: 3.14
Classifier: Programming Language :: Python :: 3.15
Classifier: Programming Language :: Python :: Implementation :: CPython
Classifier: Programming Language :: Python :: Implementation :: PyPy
Classifier: Programming Language :: Rust
Classifier: Topic :: Multimedia :: Graphics
Classifier: Topic :: Security :: Cryptography
Classifier: Typing :: Typed
Requires-Dist: numpy>=1.20.0
Requires-Dist: maturin>=1.11,<2.0 ; extra == 'dev'
Requires-Dist: pytest>=7.0 ; extra == 'dev'
Requires-Dist: ruff>=0.1.0 ; extra == 'dev'
Requires-Dist: mypy>=1.0 ; extra == 'dev'
Requires-Dist: pillow>=9.0 ; extra == 'dev'
Requires-Dist: pytest>=7.0 ; extra == 'test'
Requires-Dist: pillow>=9.0 ; extra == 'test'
Provides-Extra: dev
Provides-Extra: test
License-File: LICENSE
Summary: High-performance image pixel scrambling library written in Rust
Keywords: image,scramble,encryption,pixel,rust,pyo3
Author: LittleNyima
License: MIT
Requires-Python: >=3.8
Project-URL: Homepage, https://github.com/LittleNyima/pyscramble
Project-URL: Issues, https://github.com/LittleNyima/pyscramble/issues
Project-URL: Repository, https://github.com/LittleNyima/pyscramble
